{
  "version": 1,
  "nodes": {
    "positionGeometry": "Pozīcija",
    "positionLocal": "Lokālā pozīcija",
    "positionWorld": "Pasaules pozīcija",
    "positionView": "Skata pozīcija",
    "positionWorldDirection": "Pasaules virziens",
    "positionViewDirection": "Skata virziens",
    "cameraPosition": "Kameras pozīcija",
    "cameraNear": "Kameras tuvā plakne",
    "cameraFar": "Kameras tālā plakne",
    "normalLocal": "Normāle",
    "tangentLocal": "Pieskare",
    "time": "Laiks",
    "screenUV": "Ekrāna UV",
    "uv": "UV koordinātas",
    "property_float": "Skaitļa parametrs",
    "property_color": "Krāsas parametrs",
    "slider": "Slīdnis",
    "float": "Reālskaitlis",
    "int": "Vesels skaitlis",
    "vec2": "2D vektors",
    "vec3": "3D vektors",
    "vec4": "4D vektors",
    "color": "Krāsa",
    "add": "Saskaitīt",
    "sub": "Atņemt",
    "mul": "Reizināt",
    "div": "Dalīt",
    "sin": "Sinuss",
    "cos": "Kosinuss",
    "abs": "Modulis",
    "sqrt": "Kvadrātsakne",
    "exp": "Eksponente",
    "log2": "Binārais logaritms",
    "floor": "Noapaļot uz leju",
    "round": "Noapaļot",
    "fract": "Daļa aiz komata",
    "oneMinus": "1 − x",
    "pow": "Kāpināt",
    "mod": "Atlikums",
    "clamp": "Ierobežot",
    "min": "Minimums",
    "max": "Maksimums",
    "mix": "Sajaukt",
    "smoothstep": "Gluda pāreja",
    "remap": "Pārveidot diapazonu",
    "select": "Izvēlēties",
    "greaterThan": "Lielāks par",
    "lessThan": "Mazāks par",
    "equal": "Vienāds",
    "normalize": "Normēt",
    "length": "Garums",
    "distance": "Attālums",
    "dot": "Skalārais reizinājums",
    "cross": "Vektoriālais reizinājums",
    "split": "Sadalīt",
    "append": "Apvienot",
    "perlin": "Perlina troksnis",
    "perlinVec3": "Perlina troksnis (3D)",
    "fbm": "Fraktāļu troksnis (fBm)",
    "fbmVec3": "Fraktāļu troksnis (fBm, 3D)",
    "cellNoise": "Šūnu troksnis",
    "voronoi": "Voronoi troksnis",
    "voronoiVec2": "Voronoi troksnis (F1/F2)",
    "voronoiVec3": "Voronoi troksnis (F1/F2/F3)",
    "hsl": "HSL krāsa",
    "toHsl": "Uz HSL",
    "stripes": "Svītras",
    "dataviz": "Datu vizualizācija",
    "output": "Izvade",
    "unknown": "Nezināms",
    "dataNode": "Dati",
    "imageNode": "Attēls"
  },
  "categories": {
    "input": "Ievade",
    "type": "Tipi",
    "arithmetic": "Aritmētika",
    "math": "Matemātika",
    "interpolation": "Interpolācija",
    "logic": "Loģika",
    "vector": "Vektors",
    "noise": "Troksnis",
    "color": "Krāsa",
    "texture": "Tekstūras",
    "unknown": "Nezināms",
    "output": "Izvade"
  }
}
